en_dtypes/__init__.py
en_dtypes/_en_dtypes_ext.cpython-310-x86_64-linux-gnu.so
en_dtypes/_finfo.py
en_dtypes/py.typed
en_dtypes-0.0.4.dist-info/METADATA
en_dtypes-0.0.4.dist-info/WHEEL
en_dtypes-0.0.4.dist-info/top_level.txt
en_dtypes-0.0.4.dist-info/RECORD
en_dtypes-0.0.4.dist-info/licenses/LICENSE
en_dtypes-0.0.4.dist-info/licenses/LICENSE.eigen
