Metadata-Version: 2.1
Name: en_dtypes
Version: 0.0.4
Summary: Experimental numpy dtypes
Author: dengguojie
Author-email: dengguojie <denggj7@163.com>
License: Appache-2.0
Classifier: Programming Language :: Python :: 3
Classifier: Programming Language :: Python :: 3 :: Only
Classifier: License :: OSI Approved :: Apache Software License
Classifier: Intended Audience :: Science/Research
Requires-Python: >=3.7
License-File: LICENSE
License-File: LICENSE.eigen
Requires-Dist: numpy>1.20
Provides-Extra: dev
Requires-Dist: absl-py; extra == "dev"
Requires-Dist: pytest; extra == "dev"
Requires-Dist: pytest-xdist; extra == "dev"
Requires-Dist: pylint>=2.6.0; extra == "dev"
Requires-Dist: pyink; extra == "dev"
